lambdas/__init__.py
lambdas/contrib/__init__.py
lambdas/contrib/mypy/__init__.py
lambdas/contrib/mypy/lambdas_plugin.py
lambdas/py.typed
lambdas-0.2.0.dist-info/LICENSE
lambdas-0.2.0.dist-info/METADATA
lambdas-0.2.0.dist-info/WHEEL
lambdas-0.2.0.dist-info/RECORD
