Metadata-Version: 2.1
Name: lambdas
Version: 0.2.0
Summary: Typed lambdas that are short and readable
Home-page: https://lambdas.readthedocs.io
License: BSD-2-Clause
Keywords: functional programming,fp,lambda,lambdas,composition,type-safety,mypy,stubs
Author: sobolevn
Author-email: mail@sobolevn.me
Requires-Python: >=3.8.1,<4
Classifier: Development Status :: 4 - Beta
Classifier: Intended Audience :: Developers
Classifier: License :: OSI Approved :: BSD License
Classifier: Operating System :: OS Independent
Classifier: Programming Language :: Python :: 3
Classifier: Programming Language :: Python :: 3.9
Classifier: Programming Language :: Python :: 3.10
Classifier: Programming Language :: Python :: 3.11
Classifier: Topic :: Software Development :: Libraries :: Python Modules
Classifier: Topic :: Utilities
Classifier: Typing :: Typed
Requires-Dist: typing-extensions (>=4.0,<5.0)
Project-URL: Repository, https://github.com/dry-python/lambdas
